LICENSE.txt
MANIFEST.in
README.rst
setup.py
natsort/__init__.py
natsort/tests.py
naturalsort.egg-info/PKG-INFO
naturalsort.egg-info/SOURCES.txt
naturalsort.egg-info/dependency_links.txt
naturalsort.egg-info/top_level.txt